kakao_api/__init__.py
kakao_api/exceptions.py
kakao_api/kakao_api.py
kakao_api/types.py
kakao_api/urls.py
kakao_api/utils/__init__.py
kakao_api/utils/singleton.py
kakao_api-0.1.4.dist-info/LICENSE
kakao_api-0.1.4.dist-info/METADATA
kakao_api-0.1.4.dist-info/WHEEL
kakao_api-0.1.4.dist-info/top_level.txt
kakao_api-0.1.4.dist-info/RECORD
