Metadata-Version: 2.1
Name: kakao-api
Version: 0.1.4
Summary: 카카오 로그인 rest api
Author: no hong seok
Author-email: vet1ments@naver.com
Maintainer: no hong seok
Maintainer-email: vet1ments@naver.com
License: MIT
Project-URL: Repository, https://github.com/vet1ments/kakao_api
Requires-Python: >=3.11.0
License-File: LICENSE
Requires-Dist: pydantic >=2.0.0
Requires-Dist: httpx >=0.27.0
